{
  "version": 1,
  "skills": {
    "gsap-core": {
      "source": "greensock/gsap-skills",
      "sourceType": "github",
      "skillPath": "skills/gsap-core/SKILL.md",
      "computedHash": "c4a01101d9e1aafbf4b49f75d74f9349790d8741981ba0237c990093863035a6"
    },
    "gsap-frameworks": {
      "source": "greensock/gsap-skills",
      "sourceType": "github",
      "skillPath": "skills/gsap-frameworks/SKILL.md",
      "computedHash": "4852e85a48088d9044b08ebd1db607915b628c0c3ec7e04300713f546728fbdf"
    },
    "gsap-performance": {
      "source": "greensock/gsap-skills",
      "sourceType": "github",
      "skillPath": "skills/gsap-performance/SKILL.md",
      "computedHash": "863842ac2d7aee53fd4f0025c960173d7ad3e658a5715b89b2211fa280213c1f"
    },
    "gsap-plugins": {
      "source": "greensock/gsap-skills",
      "sourceType": "github",
      "skillPath": "skills/gsap-plugins/SKILL.md",
      "computedHash": "791bda0e6e460511fe82a78e745db519b88ffaeeab4d04a74879a03ca4f41740"
    },
    "gsap-react": {
      "source": "greensock/gsap-skills",
      "sourceType": "github",
      "skillPath": "skills/gsap-react/SKILL.md",
      "computedHash": "7d3b52822681a4158e371f895c58fb7030ecaf33f585a534b7162f9e92c5d893"
    },
    "gsap-scrolltrigger": {
      "source": "greensock/gsap-skills",
      "sourceType": "github",
      "skillPath": "skills/gsap-scrolltrigger/SKILL.md",
      "computedHash": "1cdc5647693783cb7a662d84a5de434c88a051ed56b4d33597c9b5782b5973e6"
    },
    "gsap-timeline": {
      "source": "greensock/gsap-skills",
      "sourceType": "github",
      "skillPath": "skills/gsap-timeline/SKILL.md",
      "computedHash": "54981c2feec5a9c0d57988aeb32315af32bdeadd261550d5e9db7a7b1f08b487"
    },
    "gsap-utils": {
      "source": "greensock/gsap-skills",
      "sourceType": "github",
      "skillPath": "skills/gsap-utils/SKILL.md",
      "computedHash": "1ab2387f6e694718a4f1b5acf2a4ab16e1b884c3428adf5f6b26d830f00826cf"
    },
    "threejs-fundamentals": {
      "source": "CloudAI-X/threejs-skills",
      "sourceType": "github",
      "skillPath": "skills/threejs-fundamentals/SKILL.md",
      "computedHash": "eb66d52f53f489067d602b9b62df507adb391d8220bdd1a8aae6b73e6cee578a"
    },
    "threejs-geometry": {
      "source": "CloudAI-X/threejs-skills",
      "sourceType": "github",
      "skillPath": "skills/threejs-geometry/SKILL.md",
      "computedHash": "8337bcf86621411f54ef39727b338c84890815e4b3612ce635d593dd9c321a3e"
    },
    "threejs-interaction": {
      "source": "CloudAI-X/threejs-skills",
      "sourceType": "github",
      "skillPath": "skills/threejs-interaction/SKILL.md",
      "computedHash": "1bb23f0388d39863432494ff00ea0a96ae7d093c0c6f3149fb223ba1e673fef6"
    },
    "threejs-materials": {
      "source": "CloudAI-X/threejs-skills",
      "sourceType": "github",
      "skillPath": "skills/threejs-materials/SKILL.md",
      "computedHash": "d5846d1b8254b903eacb3014486efbe331101518604b451098fd31989c3e7fe7"
    },
    "threejs-postprocessing": {
      "source": "CloudAI-X/threejs-skills",
      "sourceType": "github",
      "skillPath": "skills/threejs-postprocessing/SKILL.md",
      "computedHash": "570b86434c30ad9bdc30f4f6d4e8c04124a07dd4ccaa778d4717ecc211dc1d90"
    },
    "threejs-shaders": {
      "source": "CloudAI-X/threejs-skills",
      "sourceType": "github",
      "skillPath": "skills/threejs-shaders/SKILL.md",
      "computedHash": "6702267bd3ee70d458b54078211db36b1c3738c3faa0570e88e33dceaf478a4d"
    }
  }
}
